{
    "en": {
        "translation": {
            "nav_donate": "DONATE",
            "nav_hi": "Hi! Name of Volunteer",
            "nav_impact": "Volunteer, make your impact!",
            "nav_opp": "Oppurunities",
            "nav_comm": "Community",
            "nav_points": "Points",
            "nav_worksh": "Workshop",
            "nav_master": "MasterClass",
            "nav_impactf": "Impact Framework",
            "nav_mayors": "Mayors of impact",
            "action_save": "SAVE",
            "action_share": "SHARE",
            "action_apply": "APPLY",
            "impact_im": "Impact",
            "impact_sector": "sector",
            "impact_sector_foodsec": "Food Security",
            "impact_sector_nutrition": "Nutrition",
            "impact_sector_liv": "Livlihood",
            "impact_education": "Education",
            "det_deadl": "Deadline to apply",
            "det_spots": "Spots Left",
            "det_from": "From",
            "det_to": "To",
            "det_points": "Points",
            "banner_hours": "Hours Required",
            "banner_trans": "Transportation",
            "banner_freq": "Frequency",
            "banner_occup": "Occupation",
            "banner_opp": "Occupation Type",
            "banner_gend": "Gender",
            "banner_age": "Age",
            "banner_lang": "Languages",
            "ngo_type": "NGO Type",
            "ngo_desc": "Description",
            "ngo_watch": "Watch previous success stories",
            "ngo_exp": "Experience",
            "footer_about": "About",
            "footer_blogs": "Blogs & Media",
            "footer_careers": "Careers",
            "footer_faq": "Faqs",
            "footer_priv": "privacy",
            "footer_terms": "Terms & conditions",
            "footer_copyr": "Copyright © All Right Reserved 2021 The Volunteer Circle",
            "footer_sub": "SUBSCRIBE TO OUR NEWSLETTER",
            "footer_subdes": "Subscribe now to our newsletter to get the latest info from The Volunteer Circle",
            "footer_subbut": "SUBSCRIBE"
        }
    },
    "ar": {
        "translation": {
            "nav_donate": "تبرع",
            "nav_hi": "مرحبا, اسم المتطوع",
            "nav_impact": "تطوع ، اجعل تأثيرك!",
            "nav_opp": "فرص",
            "nav_comm": "الجماعة",
            "nav_points": "نقاط",
            "nav_worksh": "Workshop",
            "nav_master": "MasterClass",
            "nav_imapctf": "إطار التأثير",
            "nav_mayors": "رؤساء بلديات الأثر",
            "action_save": "حمل",
            "action_share": "شارك",
            "action_apply": "قدم",
            "impact_im": "تأثير",
            "impact_sector": "قطاعات",
            "impact_sector_foodsec": "أمن الطعام",
            "impact_sector_nutrition": "التغذية",
            "impact_sector_liv": "المعيشة",
            "impact_education": "الدراسة",
            "det_deadl": "الموعد النهائي للتقديم",
            "det_spots": "الأماكن الشاغرة",
            "det_from": "من",
            "det_to": "إلى",
            "det_points": "نقاط",
            "banner_hours": "الساعات المطلوبة",
            "banner_trans": "نقل",
            "banner_freq": "تردد",
            "banner_occup": "مهنة",
            "banner_opp": "نوع المهنة",
            "banner_gend": "جنس",
            "banner_age": "عمر",
            "banner_lang": "لغات",
            "ngo_type": "نوع NGO",
            "ngo_desc": "وصف",
            "ngo_watch": "شاهد قصص النجاح السابقة",
            "ngo_exp": "خبرة",
            "footer_about": "معلومات عننا",
            "footer_blogs": "المدونات والوسائط",
            "footer_careers": "المهن",
            "footer_faq": "Faqs",
            "footer_priv": "privacy",
            "footer_terms": "Terms & conditions",
            "footer_copyr": "Copyright © All Right Reserved 2021 The Volunteer Circle",
            "footer_sub": "اشترك في نشرتنا الإخبارية",
            "footer_subdes": "اشترك الآن في النشرة الإخبارية لدينا للحصول على أحدث المعلومات من The Volunteer Circle",
            "footer_subbut": "سجل"
        }
    }
}
